Kadrajan/__init__.py
Kadrajan/module.py
kadrajan-1.0.1.dist-info/METADATA
kadrajan-1.0.1.dist-info/WHEEL
kadrajan-1.0.1.dist-info/top_level.txt
kadrajan-1.0.1.dist-info/RECORD
