Metadata-Version: 2.4
Name: Kadrajan
Version: 1.0.1
Summary: Python için ilk kütüphanem
Author: Poyraz
Requires-Python: >=3.6
Dynamic: author
Dynamic: requires-python
Dynamic: summary
